ppfun/__init__.py
ppfun-1.0.5.dist-info/LICENSE
ppfun-1.0.5.dist-info/METADATA
ppfun-1.0.5.dist-info/WHEEL
ppfun-1.0.5.dist-info/top_level.txt
ppfun-1.0.5.dist-info/RECORD
