Metadata-Version: 2.1
Name: ppfun
Version: 1.0.5
Summary: Allows you to use the PixelPlanet.Fun API
Home-page: https://github.com/portasynthinca3/ppfun
Author: portasynthinca3
Author-email: portasynthinca3@gmail.com
License: UNKNOWN
Platform: UNKNOWN
Classifier: Programming Language :: Python :: 3
Classifier: License :: Freeware
Classifier: Operating System :: OS Independent
Requires-Python: >=3.6
Requires-Dist: requests
